rhizo/__init__.py
rhizo/config.py
rhizo/controller.py
rhizo/main.py
rhizo/messages.py
rhizo/resources.py
rhizo/sample_config.yaml
rhizo/sequences.py
rhizo/util.py
rhizo_client-0.1.5.dist-info/LICENSE.txt
rhizo_client-0.1.5.dist-info/METADATA
rhizo_client-0.1.5.dist-info/WHEEL
rhizo_client-0.1.5.dist-info/top_level.txt
rhizo_client-0.1.5.dist-info/RECORD
