Metadata-Version: 2.1
Name: rhizo-client
Version: 0.1.5
Summary: Client for rhizo-server
Home-page: https://github.com/rhizolab/rhizo-client
Author: Peter Sand
Author-email: rhizo@rhizolab.org
License: MIT
Platform: UNKNOWN
Classifier: Development Status :: 3 - Alpha
Classifier: Intended Audience :: Developers
Classifier: License :: OSI Approved :: MIT License
Classifier: Natural Language :: English
Classifier: Programming Language :: Python :: 2.7
Classifier: Programming Language :: Python :: 3
Classifier: Programming Language :: Python :: 3.6
Classifier: Programming Language :: Python :: 3.7
Classifier: Programming Language :: Python :: 3.8
Classifier: Programming Language :: Python :: 3.9
Requires-Python: >=2.7, <4
Requires-Dist: gevent
Requires-Dist: paho-mqtt
Requires-Dist: psutil
Requires-Dist: pyyaml (>=5)
Requires-Dist: ws4py
